pydpn/__init__.py
pydpn/_api/__init__.py
pydpn/_api/api_base.py
pydpn/_api/dashboard.py
pydpn/_api/log.py
pydpn/_api/mode.py
pydpn/_api/password.py
pydpn/_api/reboot.py
pydpn/_api/routing.py
pydpn/_api/sharing_config.py
pydpn/_api/sharing_filter.py
pydpn/_api/sharing_log.py
pydpn/_api/sharing_traffic.py
pydpn/_api/ssl_filter.py
pydpn/_api/system.py
pydpn/_api/tcp_access_control.py
pydpn/_api/traffic.py
pydpn/_api/tunnel.py
pydpn/_api/web_filter.py
pydpn/_const/__init__.py
pydpn/_const/region_contry.py
pydpn/_utils/__init__.py
pydpn/_utils/api_service.py
pydpn/_utils/cli_tools.py
pydpn/_utils/misc.py
pydpn/cli.py
pydpn/deeper_example_use.py
pydpn/deepernetwork.py
pydpn/version.py
pydpn-0.1.7.dist-info/entry_points.txt
pydpn-0.1.7.dist-info/LICENSE
pydpn-0.1.7.dist-info/METADATA
pydpn-0.1.7.dist-info/WHEEL
pydpn-0.1.7.dist-info/RECORD
