Metadata-Version: 2.1
Name: pydpn
Version: 0.1.7
Summary: python package for configuring a deeperNetwork device
License: MIT
Author: Your Name
Author-email: you@example.com
Requires-Python: >=3.9,<4.0
Classifier: License :: OSI Approved :: MIT License
Classifier: Programming Language :: Python :: 3
Classifier: Programming Language :: Python :: 3.9
Classifier: Programming Language :: Python :: 3.10
Classifier: Programming Language :: Python :: 3.11
Requires-Dist: beautifulsoup4 (>=4.11.1,<5.0.0)
Requires-Dist: lxml (>=4.9.2,<5.0.0)
Requires-Dist: pycryptodome (>=3.16.0,<4.0.0)
Requires-Dist: requests (>=2.28.1,<3.0.0)
Requires-Dist: typer (>=0.7.0,<0.8.0)
